<annotation>
	<folder>Kondisi APD</folder>
	<filename>Foto Pemenuhan APD - 8608727.jpeg</filename>
	<path>C:\Users\USER\Pictures\TBIG_labelling\Kondisi APD\Foto Pemenuhan APD - 8608727.jpeg</path>
	<source>
		<database>Unknown</database>
	</source>
	<size>
		<width>480</width>
		<height>640</height>
		<depth>3</depth>
	</size>
	<segmented>0</segmented>
	<object>
		<name>SEPATU</name>
		<pose>Unspecified</pose>
		<truncated>0</truncated>
		<difficult>0</difficult>
		<bndbox>
			<xmin>143</xmin>
			<ymin>274</ymin>
			<xmax>291</xmax>
			<ymax>379</ymax>
		</bndbox>
	</object>
	<object>
		<name>TAMBANG_SLING</name>
		<pose>Unspecified</pose>
		<truncated>0</truncated>
		<difficult>0</difficult>
		<bndbox>
			<xmin>127</xmin>
			<ymin>179</ymin>
			<xmax>288</xmax>
			<ymax>274</ymax>
		</bndbox>
	</object>
</annotation>
